pystructs/__init__.py
pystructs/base.py
pystructs/config.py
pystructs/exceptions.py
pystructs/expressions.py
pystructs/ref.py
pystructs/struct.py
pystructs/sync.py
pystructs/validate.py
pystructs/fields/__init__.py
pystructs/fields/bitfields.py
pystructs/fields/bytes_fields.py
pystructs/fields/composite.py
pystructs/fields/floats.py
pystructs/fields/integers.py
pystructs/fields/special.py
pystructs/fields/strings.py
pystructs-0.4.0.dist-info/METADATA
pystructs-0.4.0.dist-info/WHEEL
pystructs-0.4.0.dist-info/RECORD
