Metadata-Version: 2.4
Name: pystructs
Version: 0.4.0
Summary: c-like struct implementation for human
Project-URL: Homepage, https://github.com/moreal/pystructs
Project-URL: Repository, https://github.com/moreal/pystructs
Author-email: moreal <dev.moreal@gmail.com>
License-Expression: MIT
Classifier: Development Status :: 3 - Alpha
Classifier: Programming Language :: Python :: 3.13
Classifier: Programming Language :: Python :: 3.14
Requires-Python: >=3.13
